[{"add": 1, "total": 1, "commit": 1, "time": {"$date": 1513164327877}, "del": 0}, {"add": 97, "total": 98, "commit": 2, "time": {"$date": 1513164327877}, "del": 0}, {"add": 35, "total": 119, "commit": 3, "time": {"$date": 1513164327877}, "del": 14}, {"add": 17, "total": 135, "commit": 4, "time": {"$date": 1513164327877}, "del": 1}, {"add": 70, "total": 202, "commit": 5, "time": {"$date": 1513164327877}, "del": 3}, {"add": 0, "total": 202, "commit": 6, "time": {"$date": 1513164327877}, "del": 0}, {"add": 33, "total": 232, "commit": 7, "time": {"$date": 1513164327877}, "del": 3}, {"add": 1, "total": 232, "commit": 8, "time": {"$date": 1513164327877}, "del": 1}, {"add": 25, "total": 254, "commit": 9, "time": {"$date": 1513164327877}, "del": 3}, {"add": 0, "total": 254, "commit": 10, "time": {"$date": 1513164327877}, "del": 0}, {"add": 0, "total": 254, "commit": 11, "time": {"$date": 1513164327877}, "del": 0}, {"add": 33, "total": 285, "commit": 12, "time": {"$date": 1513164327877}, "del": 2}, {"add": 137, "total": 404, "commit": 13, "time": {"$date": 1513164327877}, "del": 18}, {"add": 130, "total": 530, "commit": 14, "time": {"$date": 1513164327877}, "del": 4}, {"add": 87, "total": 613, "commit": 15, "time": {"$date": 1513164327877}, "del": 4}, {"add": 89, "total": 691, "commit": 16, "time": {"$date": 1513164327877}, "del": 11}, {"add": 442, "total": 1128, "commit": 17, "time": {"$date": 1513164327877}, "del": 5}, {"add": 3, "total": 1131, "commit": 18, "time": {"$date": 1513164327877}, "del": 0}, {"add": 5, "total": 1135, "commit": 19, "time": {"$date": 1513164327877}, "del": 1}, {"add": 153, "total": 1288, "commit": 20, "time": {"$date": 1513164327877}, "del": 0}, {"add": 23, "total": 1307, "commit": 21, "time": {"$date": 1513164327877}, "del": 4}]